pumptweet-1.6.1.data/scripts/pt.sh
pumptweet-1.6.1.data/scripts/pt.py
pumptweet-1.6.1.dist-info/RECORD
pumptweet-1.6.1.dist-info/top_level.txt
pumptweet-1.6.1.dist-info/DESCRIPTION.rst
pumptweet-1.6.1.dist-info/metadata.json
pumptweet-1.6.1.dist-info/METADATA
pumptweet-1.6.1.dist-info/WHEEL
pumptweet/MLStripper.py
pumptweet/PumpTweet.py
pumptweet/PumpLogin.py
pumptweet/__init__.py
pumptweet/shorturl.py
