Metadata-Version: 2.0
Name: pumptweet
Version: 1.6.1
Summary: Cross posts from Pump.io to Twitter.
Home-page: http://github.com/dper/pumptweet
Author: Douglas Paul Perkins
Author-email: contact@dperkins.org
License: MIT
Platform: UNKNOWN
Classifier: Development Status :: 3 - Alpha
Classifier: Intended Audience :: Developers
Classifier: Intended Audience :: End Users/Desktop
Classifier: License :: OSI Approved
Classifier: License :: OSI Approved :: MIT License
Classifier: Operating System :: OS Independent
Classifier: Operating System :: MacOS :: MacOS X
Classifier: Operating System :: Microsoft :: Windows
Classifier: Operating System :: POSIX
Classifier: Programming Language :: Python :: 2
Classifier: Programming Language :: Python :: 2.7
Classifier: Topic :: Communications
Requires-Dist: pypump (>=0.5)
Requires-Dist: python-twitter (>=2.0)
Requires-Dist: BeautifulSoup (>=3.2.1)
